Alexsecdemoraw.py
mymod1/__init__.py
mymod1/unit.py
mymod2/__init__.py
mymod2/mymod2.py
zjusecdemo-1.0.5.dist-info/METADATA
zjusecdemo-1.0.5.dist-info/WHEEL
zjusecdemo-1.0.5.dist-info/top_level.txt
zjusecdemo-1.0.5.dist-info/RECORD
