Metadata-Version: 2.1
Name: zjusecdemo
Version: 1.0.5
Summary: A sample Python project, do not download it!
Author: Alex
Author-email: zhuzhuzhuzai@gmail.com
License: MIT
